mosaic/__init__.py
mosaic/__main__.py
mosaic/about.py
mosaic/configuration.py
mosaic/defaults.py
mosaic/information.py
mosaic/library.py
mosaic/metadata.py
mosaic/player.py
mosaic/settings.toml
mosaic/utilities.py
mosaic/images/__init__.py
mosaic/images/icon.png
mosaic/images/md_help.png
mosaic/images/md_info.png
mosaic/images/md_next.png
mosaic/images/md_pause.png
mosaic/images/md_play.png
mosaic/images/md_previous.png
mosaic/images/md_repeat_all.png
mosaic/images/md_repeat_none.png
mosaic/images/md_repeat_once.png
mosaic/images/md_settings.png
mosaic/images/md_shuffle.png
mosaic/images/md_stop.png
mosaic/images/nocover.png
mosaic_music-0.30.0.dist-info/LICENSE.rst
mosaic_music-0.30.0.dist-info/METADATA
mosaic_music-0.30.0.dist-info/WHEEL
mosaic_music-0.30.0.dist-info/entry_points.txt
mosaic_music-0.30.0.dist-info/top_level.txt
mosaic_music-0.30.0.dist-info/RECORD
