Metadata-Version: 2.1
Name: mosaic-music
Version: 0.30.0
Summary: A cross-platform cover art focused music player.
Home-page: https://github.com/mandeep/Mosaic
Author: Mandeep Bhutani
Author-email: mandeep@keemail.me
License: GPLv3+
Platform: UNKNOWN
Classifier: License :: OSI Approved :: GNU General Public License v3 or later (GPLv3+)
Classifier: Development Status :: 4 - Beta
Classifier: Programming Language :: Python :: 3.5
Classifier: Programming Language :: Python :: 3.6
Classifier: Programming Language :: Python :: 3.7
Requires-Dist: importlib-resources (>=0.5)
Requires-Dist: appdirs (>=1.4.0)
Requires-Dist: mutagen (>=1.37)
Requires-Dist: toml (>=0.9.2)
Requires-Dist: natsort (>=5.3.0)
